django_bleach/__init__.py
django_bleach/forms.py
django_bleach/models.py
django_bleach/utils.py
django_bleach/templatetags/__init__.py
django_bleach/templatetags/bleach_tags.py
django_bleach/tests/__init__.py
django_bleach/tests/test_forms.py
django_bleach/tests/test_modelformfield.py
django_bleach/tests/test_models.py
django_bleach/tests/test_settings.py
django_bleach/tests/test_templatetags.py
django_bleach-3.1.0.dist-info/LICENSE
django_bleach-3.1.0.dist-info/METADATA
django_bleach-3.1.0.dist-info/WHEEL
django_bleach-3.1.0.dist-info/top_level.txt
django_bleach-3.1.0.dist-info/RECORD
