Metadata-Version: 2.1
Name: django-bleach
Version: 3.1.0
Summary: Easily use bleach with Django models and templates
Home-page: https://github.com/marksweb/django-bleach
Author: Tim Heap
Maintainer: Mark Walker
Maintainer-email: theshow+django-bleach@gmail.com
License: MIT
Project-URL: Documentation, https://django-bleach.readthedocs.io/
Project-URL: Release notes, https://github.com/marksweb/django-bleach/blob/main/CHANGELOG.md
Project-URL: Issues, https://github.com/marksweb/django-bleach/issues
Project-URL: Source, https://github.com/marksweb/django-bleach
Classifier: Environment :: Web Environment
Classifier: Intended Audience :: Developers
Classifier: License :: OSI Approved :: MIT License
Classifier: Operating System :: OS Independent
Classifier: Programming Language :: Python
Classifier: Programming Language :: Python :: 3 :: Only
Classifier: Programming Language :: Python :: 3.8
Classifier: Programming Language :: Python :: 3.9
Classifier: Programming Language :: Python :: 3.10
Classifier: Programming Language :: Python :: 3.11
Classifier: Programming Language :: Python :: 3.12
Classifier: Framework :: Django :: 3.2
Classifier: Framework :: Django :: 4.0
Classifier: Framework :: Django :: 4.1
Classifier: Framework :: Django :: 4.2
Classifier: Development Status :: 5 - Production/Stable
Requires-Python: >=3.8
License-File: LICENSE
